[
 {
  "docstatus": 0,
  "doctype": "Workflow State",
  "icon": "remove",
  "modified": "2024-11-20 14:33:14.706125",
  "name": "Rejected",
  "style": "Danger",
  "workflow_state_name": "Rejected"
 },
 {
  "docstatus": 0,
  "doctype": "Workflow State",
  "icon": "",
  "modified": "2024-12-18 23:15:08.771478",
  "name": "Draft",
  "style": "",
  "workflow_state_name": "Draft"
 },
 {
  "docstatus": 0,
  "doctype": "Workflow State",
  "icon": "",
  "modified": "2025-07-03 17:42:19.073286",
  "name": "Submitted to Manufacturing",
  "style": "",
  "workflow_state_name": "Submitted to Manufacturing"
 },
 {
  "docstatus": 0,
  "doctype": "Workflow State",
  "icon": "",
  "modified": "2025-07-03 17:42:33.623205",
  "name": "Costing Done",
  "style": "",
  "workflow_state_name": "Costing Done"
 },
 {
  "docstatus": 0,
  "doctype": "Workflow State",
  "icon": "",
  "modified": "2025-07-03 17:42:46.463141",
  "name": "Approved Internally",
  "style": "",
  "workflow_state_name": "Approved Internally"
 },
 {
  "docstatus": 0,
  "doctype": "Workflow State",
  "icon": "",
  "modified": "2025-07-09 01:10:12.938937",
  "name": "Converted to Quotation",
  "style": "",
  "workflow_state_name": "Converted to Quotation"
 },
 {
  "docstatus": 0,
  "doctype": "Workflow State",
  "icon": "",
  "modified": "2025-07-17 03:50:37.475023",
  "name": "Cancelled",
  "style": "",
  "workflow_state_name": "Cancelled"
 }
]